pcbnewTransition/__init__.py
pcbnewTransition/_version.py
pcbnewTransition/eda_angle.py
pcbnewTransition/pcbnew.py
pcbnewTransition/transition.py
pcbnewtransition-0.5.2.dist-info/LICENSE
pcbnewtransition-0.5.2.dist-info/METADATA
pcbnewtransition-0.5.2.dist-info/WHEEL
pcbnewtransition-0.5.2.dist-info/top_level.txt
pcbnewtransition-0.5.2.dist-info/RECORD
