Metadata-Version: 2.1
Name: pcbnewtransition
Version: 0.5.2
Summary: Library that allows you to support both, KiCAD 6 to 9 in your plugins
Home-page: https://github.com/yaqwsx/pcbnewTransition
Author: Jan Mrázek
Author-email: email@honzamrazek.cz
License: UNKNOWN
Platform: UNKNOWN
Classifier: Programming Language :: Python :: 3
Classifier: License :: OSI Approved :: MIT License
Classifier: Operating System :: OS Independent
Requires-Python: >3.7
License-File: LICENSE
